longtrends/__init__.py
longtrends-0.6.dist-info/LICENSE
longtrends-0.6.dist-info/METADATA
longtrends-0.6.dist-info/WHEEL
longtrends-0.6.dist-info/top_level.txt
longtrends-0.6.dist-info/RECORD
