Metadata-Version: 2.1
Name: longtrends
Version: 0.6
Summary: Download long-term Google Trends
Home-page: http://github.com/mikedbjones/longtrends
Author: Mike Jones
Author-email: mikedbjones@gmail.com
License: MIT
Platform: UNKNOWN
License-File: LICENSE
Requires-Dist: pytrends
